pydartsnut/__init__.py
pydartsnut/_input_handler.py
pydartsnut/dartsnut.py
pydartsnut/py.typed
pydartsnut-1.0.1.dist-info/METADATA
pydartsnut-1.0.1.dist-info/WHEEL
pydartsnut-1.0.1.dist-info/top_level.txt
pydartsnut-1.0.1.dist-info/RECORD
