Metadata-Version: 2.4
Name: pydartsnut
Version: 1.0.1
Summary: dartsnut python package
Project-URL: Homepage, https://github.com/Dartsnut/pydartsnut
Project-URL: Bug Tracker, https://github.com/Dartsnut/pydartsnut/issues
Requires-Python: >=3.1
